yaqti/__init__.py
yaqti/__main__.py
yaqti/fetchers.py
yaqti/helpers.py
yaqti/packages.py
yaqti-2021.7.29.dist-info/WHEEL
yaqti-2021.7.29.dist-info/METADATA
yaqti-2021.7.29.dist-info/RECORD
